pyansible/__init__.py
pyansible/ansiInventory.py
pyansible/ansirunner.py
pyansible/ansivault.py
pyansible/plugins/__init__.py
pyansible/plugins/rados.py
pyansible/plugins/virsh.py
pyansible-1.0.3.dist-info/DESCRIPTION.rst
pyansible-1.0.3.dist-info/METADATA
pyansible-1.0.3.dist-info/metadata.json
pyansible-1.0.3.dist-info/RECORD
pyansible-1.0.3.dist-info/top_level.txt
pyansible-1.0.3.dist-info/WHEEL
