Metadata-Version: 2.0
Name: pyansible
Version: 1.0.3
Summary: A module for interfacing with Ansible Runner and Inventory.
Home-page: https://github.com/bdastur/spam
Author: Behzad Dastur
Author-email: bdastur@gmail.com
License: Apache Software License
Keywords: ansible
Platform: UNKNOWN
Requires-Dist: rexutil
Requires-Dist: MarkupSafe
Requires-Dist: jinja2
Requires-Dist: PyYAML
Requires-Dist: ansible (==1.9.4)
